pygcloud/__init__.py
pygcloud/_models.py
pygcloud/base_types.py
pygcloud/cmds.py
pygcloud/constants.py
pygcloud/core.py
pygcloud/deployer.py
pygcloud/events.py
pygcloud/graph_models.py
pygcloud/grapher.py
pygcloud/helpers.py
pygcloud/hooks.py
pygcloud/models.py
pygcloud/policer.py
pygcloud/policies.py
pygcloud/tools.py
pygcloud/utils.py
pygcloud/gcp/__init__.py
pygcloud/gcp/_models.py
pygcloud/gcp/catalog.py
pygcloud/gcp/labels.py
pygcloud/gcp/linker.py
pygcloud/gcp/models.py
pygcloud/gcp/utils.py
pygcloud/gcp/services/__init__.py
pygcloud/gcp/services/addresses.py
pygcloud/gcp/services/backend.py
pygcloud/gcp/services/certificate.py
pygcloud/gcp/services/firestore.py
pygcloud/gcp/services/fwd_rules.py
pygcloud/gcp/services/iam.py
pygcloud/gcp/services/identity.py
pygcloud/gcp/services/projects.py
pygcloud/gcp/services/proxies.py
pygcloud/gcp/services/pubsub.py
pygcloud/gcp/services/run.py
pygcloud/gcp/services/scheduler.py
pygcloud/gcp/services/services.py
pygcloud/gcp/services/storage.py
pygcloud/gcp/services/tasks.py
pygcloud/gcp/services/urlmap.py
pygcloud-0.0.115.dist-info/METADATA
pygcloud-0.0.115.dist-info/WHEEL
pygcloud-0.0.115.dist-info/entry_points.txt
pygcloud-0.0.115.dist-info/top_level.txt
pygcloud-0.0.115.dist-info/RECORD
