Metadata-Version: 2.1
Name: pygcloud
Version: 0.0.115
Summary: Python helper around gcloud
Author-email: Jean-Lou Dupont <jld@jldupont.com>
Project-URL: Repository, https://github.com/jldupont/pygcloud
Project-URL: Pypi, https://pypi.org/project/pygcloud/
Classifier: Programming Language :: Python :: 3
Requires-Python: >=3.9
